<?xml version='1.0' encoding='UTF-8'?>
<package version="0.0.0" uuid="nao_additional_behaviors-0d9ed6" installOnlyAtStartup="false">
 <names>
  <name lang="en_US">Nao_Additional_Behaviors</name>
 </names>
 <supportedLanguages>
  <language>en_US</language>
 </supportedLanguages>
 <descriptionLanguages>
  <language>en_US</language>
 </descriptionLanguages>
 <contents>
  <behaviorContent path="behavior_1">
   <userRequestable/>
   <nature>interactive</nature>
   <permissions/>
  </behaviorContent>
  <behaviorContent path="anim">
   <nature>interactive</nature>
   <permissions/>
  </behaviorContent>
  <behaviorContent path="establish_trust">
   <nature>interactive</nature>
   <permissions/>
  </behaviorContent>
  <behaviorContent path="yes_sir">
   <userRequestable/>
   <nature>interactive</nature>
   <names>
    <name lang="en_US">yes_sir_behavior</name>
   </names>
   <permissions/>
  </behaviorContent>
  <behaviorContent path="sadness">
   <nature>interactive</nature>
   <permissions/>
  </behaviorContent>
  <behaviorContent path="anger">
   <nature>interactive</nature>
   <permissions/>
  </behaviorContent>
  <behaviorContent path="joy">
   <nature>interactive</nature>
   <permissions/>
  </behaviorContent>
  <behaviorContent path="surprise">
   <nature>interactive</nature>
   <permissions/>
  </behaviorContent>
  <behaviorContent path="love">
   <nature>interactive</nature>
   <permissions/>
  </behaviorContent>
  <behaviorContent path="fear">
   <nature>interactive</nature>
   <permissions/>
  </behaviorContent>
  <behaviorContent path="behaviors/establish_trust">
   <nature>interactive</nature>
   <autonomous/>
   <permissions/>
  </behaviorContent>
  <behaviorContent path="behaviors/anim">
   <nature>interactive</nature>
   <permissions/>
  </behaviorContent>
  <behaviorContent path="behaviors/yes_sir">
   <nature>interactive</nature>
   <permissions/>
  </behaviorContent>
  <behaviorContent path="behaviors/sadness">
   <nature>interactive</nature>
   <permissions/>
  </behaviorContent>
  <behaviorContent path="behaviors/anger">
   <nature>interactive</nature>
   <permissions/>
  </behaviorContent>
  <behaviorContent path="behaviors/joy">
   <nature>interactive</nature>
   <permissions/>
  </behaviorContent>
  <behaviorContent path="behaviors/surprise">
   <nature>interactive</nature>
   <permissions/>
  </behaviorContent>
  <behaviorContent path="behaviors/love">
   <nature>interactive</nature>
   <permissions/>
  </behaviorContent>
  <behaviorContent path="behaviors/fear">
   <nature>interactive</nature>
   <permissions/>
  </behaviorContent>
  <behaviorContent path="behaviors/look_bottom">
   <nature>interactive</nature>
   <permissions/>
  </behaviorContent>
  <behaviorContent path="behaviors/look_top">
   <nature>interactive</nature>
   <permissions/>
  </behaviorContent>
  <behaviorContent path="behaviors/look_right">
   <nature>interactive</nature>
   <permissions/>
  </behaviorContent>
  <behaviorContent path="behaviors/look_left">
   <nature>interactive</nature>
   <permissions/>
  </behaviorContent>
  <behaviorContent path="behaviors/look_bottom_right">
   <nature>interactive</nature>
   <permissions/>
  </behaviorContent>
  <behaviorContent path="behaviors/look_bottom_left">
   <nature>interactive</nature>
   <permissions/>
  </behaviorContent>
  <behaviorContent path="behaviors/look_top_left">
   <nature>interactive</nature>
   <permissions/>
  </behaviorContent>
  <behaviorContent path="behaviors/look_top_right">
   <nature>interactive</nature>
   <permissions/>
  </behaviorContent>
  <behaviorContent path="behaviors/dance">
   <nature>interactive</nature>
   <permissions/>
  </behaviorContent>
  <behaviorContent path="showcase">
   <nature>interactive</nature>
   <autonomous/>
   <permissions/>
  </behaviorContent>
  <behaviorContent path="vision_recognition">
   <nature>interactive</nature>
   <permissions/>
  </behaviorContent>
 </contents>
</package>
